{
"urls":[
        {"url":"./recha-media.json","name":"老王追劇"},
        {"url":"./recha-live.json","name":"老王直播"},
        {"url":"./recha-sex.json","name":"老王登大人"},
        {"url":"https://robyang.us.kg/VodLive/jb8ffa","name":"RobYang點播"},
        {"url":"https://9280.kstore.space/wex.json","name":"唐三接口"},
        {"url":"https://raw.githubusercontent.com/805598571/77/f14e81d6a826e7127c36edd2f9dd989a3f1bb4b3/cs.json","name":"撿垃圾之神"},
        {"url":"https://gitlab.com/dokiss1/tvbox/-/raw/master/doki-SC.json","name":"忐忑接口-113-11-17"}
       ]
}
